puckfetcher/__init__.py
puckfetcher/__main__.py
puckfetcher/config.py
puckfetcher/constants.py
puckfetcher/error.py
puckfetcher/subscription.py
puckfetcher/test/__init__.py
puckfetcher/test/test_config.py
puckfetcher/test/test_main.py
puckfetcher/test/test_subscription.py
puckfetcher-1.5.0.dist-info/LICENSE
puckfetcher-1.5.0.dist-info/METADATA
puckfetcher-1.5.0.dist-info/WHEEL
puckfetcher-1.5.0.dist-info/entry_points.txt
puckfetcher-1.5.0.dist-info/top_level.txt
puckfetcher-1.5.0.dist-info/RECORD
