Metadata-Version: 2.1
Name: puckfetcher
Version: 1.5.0
Summary: A simple command-line podcatcher.
Home-page: https://github.com/lunemercove/puckfetcher
Download-URL: https://github.com/lunemercove/puckfetcher/archive/v1.5.0.tar.gz
Author: Luné Mercové
Author-email: puckfetcher@lune.gay
License: BSD3
Keywords: music,podcasts,rss
Classifier: Development Status :: 5 - Production/Stable
Classifier: Environment :: Console
Classifier: Intended Audience :: End Users/Desktop
Classifier: License :: OSI Approved :: BSD License
Classifier: Natural Language :: English
Classifier: Operating System :: MacOS :: MacOS X
Classifier: Operating System :: POSIX :: Linux
Classifier: Programming Language :: Python :: 3.6
Classifier: Programming Language :: Python :: 3.7
Classifier: Programming Language :: Python :: 3.8
Classifier: Programming Language :: Python :: 3.9
Classifier: Programming Language :: Python :: Implementation :: CPython
Classifier: Topic :: Multimedia :: Sound/Audio
Classifier: Topic :: Internet :: WWW/HTTP
Classifier: Topic :: Utilities
Classifier: Typing :: Typed
Requires-Python: >=3.6
License-File: LICENSE
Requires-Dist: appdirs (<2.0.0,>=1.4.4)
Requires-Dist: clint (<0.6.0,>=0.5.1)
Requires-Dist: feedparser (<7.0.0,>=6.0.10)
Requires-Dist: pyyaml (<7.0.0,>=6.0)
Requires-Dist: python-magic (<0.5.0,>=0.4.27)
Requires-Dist: requests (<3.0.0,>=2.28.1)
Requires-Dist: u-msgpack-python (<3.0.0,>=2.7.1)
Requires-Dist: eyed3 (<1.0.0,>=0.9.7)
Requires-Dist: bottilities (<2.0.0,>=1.4.0)
